{"P1": {"labels": ["documentation"], "postTitle": "P1983 [NOIP 2013 \u666e\u53ca\u7ec4] \u8f66\u7ad9\u5206\u7ea7--\u9898\u89e3", "postUrl": "post/P1983%20%5BNOIP%202013%20-pu-ji-zu-%5D%20-che-zhan-fen-ji----ti-jie.html", "createdDate": "2025-07-15", "dateLabelColor": "#0969da"}, "labelColorDict": {"bug": "#d73a4a", "documentation": "#0075ca", "duplicate": "#cfd3d7", "enhancement": "#a2eeef", "good first issue": "#7057ff", "help wanted": "#008672", "invalid": "#e4e669", "question": "#d876e3", "wontfix": "#ffffff"}}